{"notes_frontend_html.md":"DRuKMVMW","notes_devops_deploy-be.md":"CTERGMQM","notes_devops_deploy-compose.md":"CuB13jv3","notes_frontend_css.md":"BisdRlN8","notes_frontend_webpack.md":"eocE65o6","visualization_readme.md":"hUm5VxLf","notes_devops_deploy-fe.md":"L79zVb2_","notes_frontend_typescript.md":"BXgDCdcf","notes_frontend_react.md":"RP_0ko4z","visualization_plan.md":"BuUWqibV","index.md":"IyGbL03s","notes_frontend_javascript.md":"BLxIYBLL","interview_frontend.md":"siMvPDzX","notes_frontend_vue.md":"CMiqArw0","notes_backend_mysql-crash-course.md":"XEIQx4h0"}
